concurrent_executor/__init__.py
concurrent_executor/_version.py
concurrent_executor/cli.py
concurrent_executor/executor.py
concurrent_executor/io.py
concurrent_executor/signal_handler.py
concurrent_executor-1.1.2.data/scripts/cexec
concurrent_executor-1.1.2.data/scripts/cssh
concurrent_executor-1.1.2.dist-info/LICENSE
concurrent_executor-1.1.2.dist-info/METADATA
concurrent_executor-1.1.2.dist-info/WHEEL
concurrent_executor-1.1.2.dist-info/top_level.txt
concurrent_executor-1.1.2.dist-info/RECORD
